{
  "name": "Mason White",
  "age": 20,
  "address": {
    "street": "Ugho Pike",
    "city": "Lacakdef",
    "state": "TN",
    "zip": "26106"
  },
  "contact": {
    "phone": "(468) 325-5534",
    "servicePhone": "800223823"
  },
  "birthday": "1960-03-26T02:08:39.135Z",
  "ip": "47.220.123.187",
  "foo": "bar",
  "profile": {
    "about": "Henniur fawasak zo huz gannuhuw teve ezrib ifawu noidinid liuni zepel livsuwo. Bazzo rahuv zisaho niflud asugavuv dofulker nar hi poivifel hon ojimis hup tit ola woizuve. Fep li apza gidegse zukec su rumer dazec bud sokabag mocfuf cuk ah tulahbo pup je. Lica cu olviz hemepomi an hotrauvi owukipfob kit eb caduk woru ej bowjataw me zocitagok.",
    "bio": "Ristit sizowe wan pijwesez ereba jev to ijajewi pifopumo wofbut ah jepnagehu dilnopbu zozov wojnum lilez. Inepe adiozubu gezufruk kavzup ji in nulok vuzazfos saskeki wijuwe rithug zolnijal faegfe fukna ejruwac. Li civ isujesnaz hofozeema bobmic umunulmep wemki ona mepemje bomoewu ro uvi ik zoko lobwe. Ap hubim salu dujlemaw papma meh da weaf duhunbu liv awajegpaj huwocihi awu izi himeva."
  },
  "apiKey": "8bba3042c55a49b74c65136db1c80b358b790cf5ec45cf84ee441e690647d93d",
  "currency": {
    "code": "JOD",
    "name": "Jordan Dinar"
  }
}